LICENSE.txt
MANIFEST.in
README.md
setup.py
pycaustic/__init__.py
pycaustic/errors.py
pycaustic/patterns.py
pycaustic/responses.py
pycaustic/scraper.py
pycaustic/templates.py
pycaustic/version.py
pycaustic.egg-info/PKG-INFO
pycaustic.egg-info/SOURCES.txt
pycaustic.egg-info/dependency_links.txt
pycaustic.egg-info/requires.txt
pycaustic.egg-info/top_level.txt