Metadata-Version: 1.0
Name: pycaustic
Version: 0.0.36
Summary: Python adaptation of Caustic
Home-page: http://github.com/talos/pycaustic
Author: John Krauss
Author-email: john@accursedware.com
License: BSD
Platform: UNKNOWN
Classifier: Development Status :: 3 - Alpha
Classifier: Intended Audience :: Developers
Classifier: Natural Language :: English
Classifier: License :: OSI Approved :: BSD License
Classifier: Programming Language :: Python :: 2.6
Classifier: Programming Language :: Python :: 2.7
